async_messaged/__init__.py
async_messaged/__version__.py
async_messaged/daemon.py
async_messaged/py.typed
async_messaged/sb.py
async_messaged/utils.py
async_messaged/mq/__init__.py
async_messaged/mq/rfh2.py
grizzly_loadtester_extras_async_messaged-0.1.1.dist-info/METADATA
grizzly_loadtester_extras_async_messaged-0.1.1.dist-info/WHEEL
grizzly_loadtester_extras_async_messaged-0.1.1.dist-info/entry_points.txt
grizzly_loadtester_extras_async_messaged-0.1.1.dist-info/RECORD
