Metadata-Version: 2.4
Name: grizzly-loadtester-extras-async-messaged
Version: 0.1.1
Summary: Daemon for handling async messaging [for grizzly] over zmq, due to native libraries (pymqi) does not play well with gevent.
Author-email: biometria <opensource@biometria.se>
Maintainer-email: Mikael Göransson <github@mgor.se>
Requires-Python: >=3.10
Requires-Dist: azure-servicebus>=7.14.2
Requires-Dist: grizzly-loadtester-common
Requires-Dist: pyzmq==27.0.2
Requires-Dist: setproctitle>=1.3.6
Provides-Extra: mq
Requires-Dist: pymqi>=1.12.11; extra == 'mq'
